app_utils/__init__.py
app_utils/settings.py
app_utils-0.1a1.dist-info/LICENSE
app_utils-0.1a1.dist-info/METADATA
app_utils-0.1a1.dist-info/WHEEL
app_utils-0.1a1.dist-info/top_level.txt
app_utils-0.1a1.dist-info/RECORD
